git_multiple_commands/__init__.py
git_multiple_commands/gmc.py
git_multiple_commands-0.1.1.dist-info/entry_points.txt
git_multiple_commands-0.1.1.dist-info/METADATA
git_multiple_commands-0.1.1.dist-info/WHEEL
git_multiple_commands-0.1.1.dist-info/RECORD
